autodeploydocker/__init__.py
autodeploydocker/main.py
autodeploydocker/prompts.py
autodeploydocker-2025.12.21144536.dist-info/METADATA
autodeploydocker-2025.12.21144536.dist-info/WHEEL
autodeploydocker-2025.12.21144536.dist-info/top_level.txt
autodeploydocker-2025.12.21144536.dist-info/RECORD
