Metadata-Version: 2.4
Name: autodeploydocker
Version: 2025.12.21144536
Summary: A new package that simplifies the deployment of Docker and Docker Compose applications to servers without requiring configuration changes or causing downtime. It automates the process, making it acces
Author-email: autodeploydocker <hi@eugene.plus>
License: MIT
Project-URL: Homepage, https://github.com/chigwell/autodeploydocker
Requires-Python: >=3.9
Requires-Dist: langchain-llm7>=0.0.0
Requires-Dist: llmatch-messages>=0.0.0
Requires-Dist: langchain-core>=0.3.0
